kenkou/__init__.py
kenkou/certcheck.py
kenkou/cmdline.py
kenkou/cmdline.py.bak
kenkou/dnscheck.py
kenkou/dnscheck.py.bak
kenkou/urlcheck.py
kenkou/urlcheck.py.bak
kenkou-0.5.5.dist-info/DESCRIPTION.rst
kenkou-0.5.5.dist-info/entry_points.txt
kenkou-0.5.5.dist-info/METADATA
kenkou-0.5.5.dist-info/metadata.json
kenkou-0.5.5.dist-info/RECORD
kenkou-0.5.5.dist-info/top_level.txt
kenkou-0.5.5.dist-info/WHEEL
