Metadata-Version: 2.0
Name: kenkou
Version: 0.5.5
Summary: A python based tool to check that a given resource (URL, Certificate and DNS entry) is alive and valid.
Home-page: https://github.com/bear/kenkou
Author: Mike Taylor
Author-email: bear@bear.im
License: MIT
Download-URL: https://pypi.python.org/pypi/kenkou
Platform: Any
Classifier: Development Status :: 4 - Beta
Classifier: Intended Audience :: Developers
Classifier: Operating System :: OS Independent
Classifier: License :: OSI Approved :: MIT License
Classifier: Programming Language :: Python
Classifier: Programming Language :: Python :: 2
Classifier: Programming Language :: Python :: 2.7
Classifier: Programming Language :: Python :: 3
Classifier: Programming Language :: Python :: 3.3
Classifier: Programming Language :: Python :: 3.4
Classifier: Programming Language :: Python :: 3.5
Classifier: Topic :: Software Development :: Libraries :: Python Modules
